alert2me/__init__.py
alert2me/alme
alert2me/configure.py
alert2me/constant.py
alert2me/run.py
alert2me/slack.py
alert2me-0.0.2.dist-info/LICENSE
alert2me-0.0.2.dist-info/METADATA
alert2me-0.0.2.dist-info/WHEEL
alert2me-0.0.2.dist-info/entry_points.txt
alert2me-0.0.2.dist-info/top_level.txt
alert2me-0.0.2.dist-info/RECORD
